modern_python/__init__.py
modern_python/console.py
modern_python/wikipedia.py
modern_python-0.3.2.dist-info/entry_points.txt
modern_python-0.3.2.dist-info/LICENSE
modern_python-0.3.2.dist-info/WHEEL
modern_python-0.3.2.dist-info/METADATA
modern_python-0.3.2.dist-info/RECORD
