Metadata-Version: 2.1
Name: modern-python
Version: 0.3.2
Summary: 现代化的python项目模版
Home-page: https://github.com/liuxd2018/modern-python
License: MIT
Author: Liu Xiaodong
Author-email: liuxd2018@foxmail.com
Requires-Python: >=3.9,<4.0
Classifier: License :: OSI Approved :: MIT License
Classifier: Programming Language :: Python :: 3
Classifier: Programming Language :: Python :: 3.9
Requires-Dist: click (>=7.1.2,<8.0.0)
Requires-Dist: desert (>=2020.11.18,<2021.0.0)
Requires-Dist: marshmallow (>=3.9.1,<4.0.0)
Requires-Dist: requests (>=2.24.0,<3.0.0)
Project-URL: Repository, https://github.com/liuxd2018/modern-python
